A2_210962012/lab1/example4/example4.v
module example4(a,b,c,d,f,g);
input a,b,c,d;
output f,g;
nand(p,a,b);
xor(f,d,p,c);
nor(g,d,b,c);
endmodule

A2_210962012/lab1/example4/example4_tb.v
`timescale 1ns/1ns
`include "example4.v"
 module example4_tb();
 reg a,b,c,d;
 wire f,g;
 example4 ex4(a,b,c,d,f,g);

 initial
 begin
 	$dumpfile("example4_tb.vcd");
 	$dumpvars(0,example4_tb);
 	a=1'b0; b=1'b0; c=1'b0;d=1'b0;
	#20;
	a=1'b0; b=1'b0; c=1'b0;d=1'b1;
	#20;
	a=1'b0; b=1'b0; c=1'b1;d=1'b1;
	#20;
	a=1'b0; b=1'b1; c=1'b0;d=1'b0;
	#20;
	a=1'b0; b=1'b1; c=1'b0;d=1'b1;
	#20;
	a=1'b0; b=1'b1; c=1'b1;d=1'b0;
	#20;
	a=1'b0; b=1'b1; c=1'b1;d=1'b1;
	#20;
	a=1'b1; b=1'b0; c=1'b0;d=1'b0;
	#20;
	a=1'b1; b=1'b0; c=1'b0;d=1'b1;
	#20;
	a=1'b1; b=1'b0; c=1'b1;d=1'b0;
	#20;
	a=1'b1; b=1'b0; c=1'b1;d=1'b1;
	#20;
	a=1'b1; b=1'b1; c=1'b0;d=1'b0;
	#20;
	a=1'b1; b=1'b1; c=1'b0;d=1'b1;
	#20;
	a=1'b1; b=1'b1; c=1'b1;d=1'b0;
	#20;
	a=1'b1; b=1'b1; c=1'b1;d=1'b1;
	#20;
	
	
	$display("Test complete");
end
endmodule

A2_210962012/lab1/example4/example4_tb.vcd
$date
	Wed Aug 24 11:19:06 2022
$end
$version
	Icarus Verilog
$end
$timescale
	1ns
$end
$scope module example4_tb $end
$var wire 1 ! g $end
$var wire 1 " f $end
$var reg 1 # a $end
$var reg 1 $ b $end
$var reg 1 % c $end
$var reg 1 & d $end
$scope module ex4 $end
$var wire 1 # a $end
$var wire 1 $ b $end
$var wire 1 % c $end
$var wire 1 & d $end
$var wire 1 " f $end
$var wire 1 ! g $end
$var wire 1 ' p $end
$upscope $end
$upscope $end
$enddefinitions $end
#0
$dumpvars
1'
0&
0%
0$
0#
1"
1!
$end
#20
0"
0!
1&
#40
1"
1%
#60
0&
0%
1$
#80
0"
1&
#100
0&
1%
#120
1"
1&
#140
1!
0&
0%
0$
1#
#160
0"
0!
1&
#180
0&
1%
#200
1"
1&
#220
0"
0'
0&
0%
1$
#240
1"
1&
#260
0&
1%
#280
0"
1&
