lab5/question2/decoder3to8.v
module decoder3to8(W, Y, En);
input [2:0] W;
input En;

output [0:7] Y;
reg [0:7] Y;

always @(W or En)
if(En==0)
Y=0;
else if(W==0)
Y=0;
else if(W==1)
Y=1;
else if(Y==2)
Y=2;
else if(Y==3)
Y=3;
else if(Y==4)
Y=4;
else if(Y==5)
Y=5;
else if(Y==6)
Y=6;
else
Y=7;   
endmodule

lab5/question2/decoder3to8_tb.v
`timescale 1ns/1ns
`include "decoder3to8.v"
module decoder3to8_tb();

reg [2:0]W;
reg En;
wire [7:0]Y;

decoder3to8 d24(W, Y, En);
    initial
    begin
    $dumpfile("decoder3to8_tb.vcd");
    $dumpvars(0, decoder3to8_tb);
    
    En=0;W[2]=0;W[1]=0;W[0]=0;#20;
    En=1;W[2]=0;W[1]=0;W[0]=0;#20;
    En=1;W[2]=0;W[1]=0;W[0]=1;#20;
    En=1;W[2]=0;W[1]=1;W[0]=0;#20;
    En=1;W[2]=0;W[1]=1;W[0]=1;#20;
    En=1;W[2]=1;W[1]=0;W[0]=0;#20;
    En=1;W[2]=1;W[1]=0;W[0]=1;#20;
    En=1;W[2]=1;W[1]=1;W[0]=0;#20;
    En=1;W[2]=1;W[1]=1;W[0]=1;#20;
    
    $display("Test Completed");
    end
endmodule

lab5/question2/decoder3to8_tb.vcd
$date
	Wed Oct 12 11:10:37 2022
$end
$version
	Icarus Verilog
$end
$timescale
	1ns
$end
$scope module decoder3to8_tb $end
$var wire 8 ! Y [7:0] $end
$var reg 1 " En $end
$var reg 3 # W [2:0] $end
$scope module d24 $end
$var wire 1 " En $end
$var wire 3 $ W [2:0] $end
$var reg 8 % Y [0:7] $end
$upscope $end
$upscope $end
$enddefinitions $end
#0
$dumpvars
b0 %
b0 $
b0 #
0"
b0 !
$end
#20
1"
#40
b1 !
b1 %
b1 #
b1 $
#60
b111 !
b111 %
b10 #
b10 $
#80
b11 #
b11 $
#100
b100 #
b100 $
#120
b101 #
b101 $
#140
b110 #
b110 $
#160
b111 #
b111 $
