A2_210962012/lab2/program1/example1.v
module example1(x1,x2,x3,f);
input x1,x2,x3;
output f;
assign f= x1 &(x2|x3);
endmodule

A2_210962012/lab2/program1/example1_tb.v
`timescale 1ns/1ns
`include "example1.v"

module example1_tb();
reg x1,x2,x3;
wire f;
example1 ex1(x1,x2,x3,f);

initial 
begin

	$dumpfile("example1_tb.vcd");
 	$dumpvars(0,example1_tb);
 	x1=1'b0; x2=1'b0; x3=1'b0;
	#20;
	x1=1'b0; x2=1'b0; x3=1'b1;
	#20;
	x1=1'b0; x2=1'b1; x3=1'b0;
	#20;
	x1=1'b0; x2=1'b1; x3=1'b1;
	#20;
	x1=1'b1; x2=1'b0; x3=1'b0;
	#20;
	x1=1'b1; x2=1'b0; x3=1'b1;
	#20;
	x1=1'b1; x2=1'b1; x3=1'b0;
	#20;
	x1=1'b1; x2=1'b1; x3=1'b1;
	#20;
	
	
	$display("Test complete");
end
endmodule

A2_210962012/lab2/program1/example1_tb.vcd
$date
	Wed Sep  7 09:25:33 2022
$end
$version
	Icarus Verilog
$end
$timescale
	1ns
$end
$scope module example1_tb $end
$var wire 1 ! f $end
$var reg 1 " x1 $end
$var reg 1 # x2 $end
$var reg 1 $ x3 $end
$scope module ex1 $end
$var wire 1 ! f $end
$var wire 1 " x1 $end
$var wire 1 # x2 $end
$var wire 1 $ x3 $end
$upscope $end
$upscope $end
$enddefinitions $end
#0
$dumpvars
0$
0#
0"
0!
$end
#20
1$
#40
0$
1#
#60
1$
#80
0!
0$
0#
1"
#100
1!
1$
#120
0$
1#
#140
1$
